flask_driver8/__init__.py
flask_driver8/__main__.py
flask_driver8/driver8_blueprint.py
Flask_Driver8-0.0.3.dist-info/LICENSE
Flask_Driver8-0.0.3.dist-info/METADATA
Flask_Driver8-0.0.3.dist-info/WHEEL
Flask_Driver8-0.0.3.dist-info/entry_points.txt
Flask_Driver8-0.0.3.dist-info/top_level.txt
Flask_Driver8-0.0.3.dist-info/RECORD
