Metadata-Version: 2.1
Name: Flask-Driver8
Version: 0.0.3
Summary: WebDriver server support for Flask applications
Home-page: https://dev.azure.com/pumpitup/pumpo-number-five/
Author: Gerogij Boljuba
Author-email: georgij.boljuba@pumpitup.cz
License: Apache 2.0
Platform: any
Classifier: Environment :: Web Environment
Classifier: Intended Audience :: Developers
Classifier: Intended Audience :: Information Technology
Classifier: License :: OSI Approved :: Apache Software License
Classifier: Programming Language :: Python :: 3
Classifier: Programming Language :: Python :: 3.7
Requires-Dist: Flask
